pyserials/__init__.py
pyserials/compare.py
pyserials/format.py
pyserials/nested_dict.py
pyserials/property_dict.py
pyserials/read.py
pyserials/update.py
pyserials/validate.py
pyserials/write.py
pyserials/exception/__init__.py
pyserials/exception/_base.py
pyserials/exception/read.py
pyserials/exception/update.py
pyserials/exception/validate.py
pyserials-0.1.1.dist-info/METADATA
pyserials-0.1.1.dist-info/WHEEL
pyserials-0.1.1.dist-info/top_level.txt
pyserials-0.1.1.dist-info/RECORD
