Metadata-Version: 2.4
Name: PySerials
Version: 0.1.1
Requires-Python: >=3.10
Requires-Dist: jsonschema<5,>=4.21.0
Requires-Dist: referencing>=0.35.1
Requires-Dist: jsonpath-ng<2,>=1.6.1
Requires-Dist: ruamel.yaml>=0.18
Requires-Dist: ruamel.yaml.string<1,>=0.1.1
Requires-Dist: tomlkit<0.14,>=0.11.8
Requires-Dist: MDit<0.2,>=0.1
Requires-Dist: ExceptionMan<0.2,>=0.1
Requires-Dist: ProtocolMan<0.2,>=0.1
